kernel_tuner/__init__.py
kernel_tuner/accuracy.py
kernel_tuner/backends/__init__.py
kernel_tuner/backends/backend.py
kernel_tuner/backends/compiler.py
kernel_tuner/backends/cupy.py
kernel_tuner/backends/hip/__init__.py
kernel_tuner/backends/hip/hip.py
kernel_tuner/backends/hip/util.py
kernel_tuner/backends/hypertuner.py
kernel_tuner/backends/nvcuda.py
kernel_tuner/backends/opencl.py
kernel_tuner/backends/pycuda.py
kernel_tuner/core.py
kernel_tuner/energy/__init__.py
kernel_tuner/energy/energy.py
kernel_tuner/file_utils.py
kernel_tuner/hyper.py
kernel_tuner/integration.py
kernel_tuner/interface.py
kernel_tuner/kernelbuilder.py
kernel_tuner/observers/__init__.py
kernel_tuner/observers/compiler.py
kernel_tuner/observers/cupy.py
kernel_tuner/observers/hip.py
kernel_tuner/observers/ncu.py
kernel_tuner/observers/nvcuda.py
kernel_tuner/observers/nvml.py
kernel_tuner/observers/observer.py
kernel_tuner/observers/opencl.py
kernel_tuner/observers/pmt.py
kernel_tuner/observers/powersensor.py
kernel_tuner/observers/pycuda.py
kernel_tuner/observers/register.py
kernel_tuner/observers/tegra.py
kernel_tuner/runners/__init__.py
kernel_tuner/runners/runner.py
kernel_tuner/runners/sequential.py
kernel_tuner/runners/simulation.py
kernel_tuner/schema/T1/1.0.0/input-schema.json
kernel_tuner/schema/T4/1.0.0/metadata-schema.json
kernel_tuner/schema/T4/1.0.0/results-schema.json
kernel_tuner/searchspace.py
kernel_tuner/strategies/__init__.py
kernel_tuner/strategies/basinhopping.py
kernel_tuner/strategies/bayes_opt.py
kernel_tuner/strategies/brute_force.py
kernel_tuner/strategies/common.py
kernel_tuner/strategies/diff_evo.py
kernel_tuner/strategies/dual_annealing.py
kernel_tuner/strategies/firefly_algorithm.py
kernel_tuner/strategies/genetic_algorithm.py
kernel_tuner/strategies/greedy_ils.py
kernel_tuner/strategies/greedy_mls.py
kernel_tuner/strategies/hillclimbers.py
kernel_tuner/strategies/minimize.py
kernel_tuner/strategies/mls.py
kernel_tuner/strategies/ordered_greedy_mls.py
kernel_tuner-1.3.1.dist-info/METADATA
kernel_tuner-1.3.1.dist-info/WHEEL
kernel_tuner-1.3.1.dist-info/entry_points.txt
kernel_tuner-1.3.1.dist-info/licenses/LICENSE
kernel_tuner-1.3.1.dist-info/RECORD
