Metadata-Version: 2.4
Name: kernel_tuner
Version: 1.3.1
Summary: An easy to use CUDA/OpenCL kernel tuner in Python
License-Expression: Apache-2.0
License-File: LICENSE
Keywords: auto-tuning,gpu,computing,pycuda,cuda,pyopencl,opencl
Author: Ben van Werkhoven
Author-email: b.vanwerkhoven@esciencecenter.nl
Requires-Python: >=3.10,<4
Classifier: Environment :: Console
Classifier: Environment :: GPU
Classifier: Development Status :: 5 - Production/Stable
Classifier: Intended Audience :: Developers
Classifier: Intended Audience :: Education
Classifier: Intended Audience :: Science/Research
Classifier: License :: OSI Approved :: Apache Software License
Classifier: Natural Language :: English
Classifier: Operating System :: MacOS :: MacOS X
Classifier: Operating System :: POSIX :: Linux
Classifier: Topic :: Scientific/Engineering
Classifier: Topic :: Software Development
Classifier: Topic :: System :: Distributed Computing
Classifier: Programming Language :: Python :: 3.10
Classifier: Programming Language :: Python :: 3.11
Classifier: Programming Language :: Python :: 3.12
Classifier: Programming Language :: Python :: 3.13
Provides-Extra: cuda
Provides-Extra: cuda-opencl
Provides-Extra: hip
Provides-Extra: opencl
Provides-Extra: tutorial
Requires-Dist: hip-python ; extra == "hip"
Requires-Dist: jsonschema
Requires-Dist: jupyter (>=1.0.0) ; extra == "tutorial"
Requires-Dist: matplotlib (>=3.5.0) ; extra == "tutorial"
Requires-Dist: numpy (>=2.0.0)
Requires-Dist: nvidia-ml-py (>=12.535.108) ; extra == "cuda"
Requires-Dist: nvidia-ml-py (>=12.535.108) ; extra == "tutorial"
Requires-Dist: packaging
Requires-Dist: pandas (>=2.0.0)
Requires-Dist: pycuda (>=2024.1) ; extra == "cuda-opencl"
Requires-Dist: pycuda (>=2025.1) ; extra == "cuda"
Requires-Dist: pynvml (>=11.4.1) ; extra == "cuda"
Requires-Dist: pyopencl ; extra == "cuda-opencl"
Requires-Dist: pyopencl ; extra == "opencl"
Requires-Dist: python-constraint2 (>=2.4.0)
Requires-Dist: scikit-learn (>=1.0.2)
Requires-Dist: scipy (>=1.14.1)
Requires-Dist: xmltodict
Project-URL: Documentation, https://KernelTuner.github.io/kernel_tuner/
Project-URL: Homepage, https://KernelTuner.github.io/kernel_tuner/
Project-URL: Repository, https://github.com/KernelTuner/kernel_tuner
Project-URL: changelog, https://github.com/KernelTuner/kernel_tuner/blob/master/CHANGELOG.md
Project-URL: issues, https://github.com/KernelTuner/kernel_tuner/issues
